test/__init__.py
test/dealer_cache_test.py
test/utils_test.py
zaidan/Cache.py
zaidan/DealerCache.py
zaidan/DealerDatabase.py
zaidan/InventoryManager.py
zaidan/__init__.py
zaidan/logger.py
zaidan/utils.py
zaidan-0.1.1.dist-info/LICENSE
zaidan-0.1.1.dist-info/METADATA
zaidan-0.1.1.dist-info/WHEEL
zaidan-0.1.1.dist-info/top_level.txt
zaidan-0.1.1.dist-info/RECORD
