Metadata-Version: 2.1
Name: zaidan
Version: 0.1.1
Summary: Common utilities for the Zaidan system.
Home-page: https://github.com/ParadigmFoundation/zaidan-common
Author: Henry Harder
Author-email: henry@paradigm.market
License: MIT
Platform: UNKNOWN
Classifier: Programming Language :: Python :: 3
Classifier: License :: OSI Approved :: MIT License
Classifier: Operating System :: OS Independent
Requires-Dist: json-logging
Requires-Dist: redis
Requires-Dist: mysql-connector
Requires-Dist: requests
